soliscloud_api/__init__.py
soliscloud_api/client.py
soliscloud_api/entities.py
soliscloud_api/helpers.py
soliscloud_api/types.py
soliscloud_api-1.3.0.dist-info/METADATA
soliscloud_api-1.3.0.dist-info/WHEEL
soliscloud_api-1.3.0.dist-info/licenses/LICENSE
soliscloud_api-1.3.0.dist-info/RECORD
