Metadata-Version: 2.4
Name: soliscloud-api
Version: 1.3.0
Summary: SolisCloud API wrapper for python
Project-URL: Homepage, https://github.com/hultenvp/soliscloud-api
Project-URL: Bug Tracker, https://github.com/hultenvp/soliscloud-api/issues
Author-email: Peter van Hulten <peter.vanhulten@gmx.net>
License-File: LICENSE
Classifier: License :: OSI Approved :: MIT License
Classifier: Operating System :: OS Independent
Classifier: Programming Language :: Python :: 3
Requires-Python: >=3.7
Requires-Dist: aiohttp
Requires-Dist: async-timeout
Requires-Dist: asyncio
Requires-Dist: datetime
Requires-Dist: pybase64
Requires-Dist: throttler
Requires-Dist: typing
